spectrax/__init__.py
spectrax/__main__.py
spectrax/_diagnostics.py
spectrax/_initialization.py
spectrax/_initialize_xv.py
spectrax/_inverse_transform.py
spectrax/_model.py
spectrax/_plot.py
spectrax/_simulation.py
spectrax/version.py
spectrax-0.1.2.dist-info/licenses/LICENSE
spectrax-0.1.2.dist-info/METADATA
spectrax-0.1.2.dist-info/WHEEL
spectrax-0.1.2.dist-info/entry_points.txt
spectrax-0.1.2.dist-info/top_level.txt
spectrax-0.1.2.dist-info/RECORD
